setup.py
easy_phi/__init__.py
easy_phi/app.py
easy_phi/auth.py
easy_phi/hislip.py
easy_phi/hwal.py
easy_phi/hwconf.py
easy_phi/mod_conf_patch.py
easy_phi/scpi2widgets.py
easy_phi/utils.py
easy_phi.egg-info/PKG-INFO
easy_phi.egg-info/SOURCES.txt
easy_phi.egg-info/dependency_links.txt
easy_phi.egg-info/entry_points.txt
easy_phi.egg-info/requires.txt
easy_phi.egg-info/top_level.txt
easy_phi/static/css/style.css
easy_phi/static/css/themes/redmond/jquery-ui.min.css
easy_phi/static/css/themes/redmond/images/ui-bg_flat_0_aaaaaa_40x100.png
easy_phi/static/css/themes/redmond/images/ui-bg_flat_55_fbec88_40x100.png
easy_phi/static/css/themes/redmond/images/ui-bg_glass_75_d0e5f5_1x400.png
easy_phi/static/css/themes/redmond/images/ui-bg_glass_85_dfeffc_1x400.png
easy_phi/static/css/themes/redmond/images/ui-bg_glass_95_fef1ec_1x400.png
easy_phi/static/css/themes/redmond/images/ui-bg_gloss-wave_55_5c9ccc_500x100.png
easy_phi/static/css/themes/redmond/images/ui-bg_inset-hard_100_f5f8f9_1x100.png
easy_phi/static/css/themes/redmond/images/ui-bg_inset-hard_100_fcfdfd_1x100.png
easy_phi/static/css/themes/redmond/images/ui-icons_217bc0_256x240.png
easy_phi/static/css/themes/redmond/images/ui-icons_2e83ff_256x240.png
easy_phi/static/css/themes/redmond/images/ui-icons_469bdd_256x240.png
easy_phi/static/css/themes/redmond/images/ui-icons_6da8d5_256x240.png
easy_phi/static/css/themes/redmond/images/ui-icons_cd0a0a_256x240.png
easy_phi/static/css/themes/redmond/images/ui-icons_d8e7f3_256x240.png
easy_phi/static/css/themes/redmond/images/ui-icons_f9bd01_256x240.png
easy_phi/static/css/themes/smoothness/jquery-ui.min.css
easy_phi/static/css/themes/smoothness/images/ui-bg_flat_0_aaaaaa_40x100.png
easy_phi/static/css/themes/smoothness/images/ui-bg_flat_75_ffffff_40x100.png
easy_phi/static/css/themes/smoothness/images/ui-bg_glass_55_fbf9ee_1x400.png
easy_phi/static/css/themes/smoothness/images/ui-bg_glass_65_ffffff_1x400.png
easy_phi/static/css/themes/smoothness/images/ui-bg_glass_75_dadada_1x400.png
easy_phi/static/css/themes/smoothness/images/ui-bg_glass_75_e6e6e6_1x400.png
easy_phi/static/css/themes/smoothness/images/ui-bg_glass_95_fef1ec_1x400.png
