Metadata-Version: 1.1
Name: easy-phi
Version: 0.4
Summary: Easy Phi project web application
Home-page: https://github.com/QuantumCMU/easy_phi_API
Author: Team Quantum
Author-email: shadeless@ya.ru
License: GPL v3.0
Download-URL: http://github.com/QuantumCMU/easy_phi_API/archive/master.zip
Keywords: measurement equipment,SCPI,udev,TMC,VISA
Platform: UNKNOWN
Classifier: Programming Language :: Python :: 2
Classifier: License :: OSI Approved :: GNU General Public License v3 (GPLv3)
Classifier: Operating System :: POSIX :: Linux
Classifier: Development Status :: 1 - Planning
Classifier: Intended Audience :: Science/Research
Classifier: Topic :: Scientific/Engineering :: Interface Engine/Protocol Translator
